chatllm/__init__.py
chatllm/chatyuan.py
chatllm/embedding.py
chatllm/_his/FaissANN.py
chatllm/_his/__init__.py
chatllm/_his/_chatllm.py
chatllm/_his/_qa.py
chatllm/api/README.md
chatllm/api/__init__.py
chatllm/api/openai-api.py
chatllm/api/stream_api.py
chatllm/applications/Question2Answer.py
chatllm/applications/__init__.py
chatllm/applications/_chatann.py
chatllm/applications/chatann.py
chatllm/applications/chataudio.py
chatllm/applications/chatbase.py
chatllm/applications/chatcrawler.py
chatllm/applications/chatdoc.py
chatllm/applications/chatmind.py
chatllm/applications/chatpdf.py
chatllm/applications/chatsearch.py
chatllm/applications/chatweb.py
chatllm/applications/chatwhoosh.py
chatllm/applications/pipeline.py
chatllm/clis/README.md
chatllm/clis/__init__.py
chatllm/clis/cli.py
chatllm/llm_models/__init__.py
chatllm/llm_models/chatglm.py
chatllm/llm_models/llama_ziya.py
chatllm/utils/__init__.py
chatllm/utils/_textsplitter.py
chatllm/utils/common.py
chatllm/utils/gpu_utils.py
chatllm/webui/__init__.py
chatllm/webui/chatbase.py
chatllm/webui/chatpdf.py
chatllm/webui/conf.yaml
chatllm/webui/gradio_ui.py
chatllm/webui/nice_ui.py
chatllm/webui/run.sh
closeai-2023.5.24.11.21.58.dist-info/AUTHORS.rst
closeai-2023.5.24.11.21.58.dist-info/LICENSE
closeai-2023.5.24.11.21.58.dist-info/METADATA
closeai-2023.5.24.11.21.58.dist-info/WHEEL
closeai-2023.5.24.11.21.58.dist-info/entry_points.txt
closeai-2023.5.24.11.21.58.dist-info/top_level.txt
closeai-2023.5.24.11.21.58.dist-info/RECORD
