Metadata-Version: 2.1
Name: closeai
Version: 2023.5.24.11.21.58
Summary: Create a Python package.
Home-page: https://github.com/yuanjie-ai/ChatLLM
Author: yuanjie
Author-email: 313303303@qq.com
License: MIT license
Keywords: chatllm
Classifier: Development Status :: 2 - Pre-Alpha
Classifier: Intended Audience :: Developers
Classifier: License :: OSI Approved :: MIT License
Classifier: Natural Language :: English
Classifier: Programming Language :: Python :: 3
Classifier: Programming Language :: Python :: 3.6
Classifier: Programming Language :: Python :: 3.7
Classifier: Programming Language :: Python :: 3.8
Requires-Python: >=3.7
License-File: LICENSE
License-File: AUTHORS.rst
Requires-Dist: meutils
Requires-Dist: transformers
Requires-Dist: tokenizers
Requires-Dist: sentence-transformers
Requires-Dist: cpm-kernels
Provides-Extra: all
Requires-Dist: fastapi ; extra == 'all'
Requires-Dist: pandas (==1.5.3) ; extra == 'all'
Requires-Dist: streamlit ; extra == 'all'
Requires-Dist: pymupdf ; extra == 'all'
Requires-Dist: qdrant-client ; extra == 'all'
Requires-Dist: flask ; extra == 'all'
Provides-Extra: ann
Requires-Dist: qdrant-client ; extra == 'ann'
Provides-Extra: api
Requires-Dist: fastapi ; extra == 'api'
Requires-Dist: flask ; extra == 'api'
Provides-Extra: pdf
Requires-Dist: pymupdf ; extra == 'pdf'
Requires-Dist: streamlit ; extra == 'pdf'
Requires-Dist: pandas (==1.5.3) ; extra == 'pdf'
Provides-Extra: streamlit
Requires-Dist: streamlit ; extra == 'streamlit'
